AUTHORS
LICENSE
MANIFEST.in
README.rst
setup.py
music/__init__.py
music/admin.py
music/generator.py
music/importer.py
music/models.py
music/tests.py
music/urls.py
music/utils.py
music/views.py
music/fixtures/photosizes.json
music/management/__init__.py
music/management/commands/__init__.py
music/management/commands/importtracks.py
music/templates/music/audioembed_detail.html
music/templates/music/inclusion_tags/track_peek.html
panya_music.egg-info/PKG-INFO
panya_music.egg-info/SOURCES.txt
panya_music.egg-info/dependency_links.txt
panya_music.egg-info/not-zip-safe
panya_music.egg-info/requires.txt
panya_music.egg-info/top_level.txt